rivalcfg/__init__.py
rivalcfg/__main__.py
rivalcfg/cli.py
rivalcfg/color_helpers.py
rivalcfg/debug.py
rivalcfg/helpers.py
rivalcfg/mouse.py
rivalcfg/mouse_settings.py
rivalcfg/udev.py
rivalcfg/usbhid.py
rivalcfg/version.py
rivalcfg/devices/__init__.py
rivalcfg/devices/aerox3.py
rivalcfg/devices/aerox3_wireless_wired.py
rivalcfg/devices/aerox3_wireless_wireless.py
rivalcfg/devices/aerox5.py
rivalcfg/devices/aerox5_wireless_wired.py
rivalcfg/devices/aerox5_wireless_wireless.py
rivalcfg/devices/aerox9_wireless_wired.py
rivalcfg/devices/aerox9_wireless_wireless.py
rivalcfg/devices/kanav2.py
rivalcfg/devices/kinzuv2.py
rivalcfg/devices/prime.py
rivalcfg/devices/prime_mini.py
rivalcfg/devices/prime_wireless_wired.py
rivalcfg/devices/prime_wireless_wireless.py
rivalcfg/devices/rival100.py
rivalcfg/devices/rival110.py
rivalcfg/devices/rival3.py
rivalcfg/devices/rival300.py
rivalcfg/devices/rival300s.py
rivalcfg/devices/rival310.py
rivalcfg/devices/rival3_wireless.py
rivalcfg/devices/rival500.py
rivalcfg/devices/rival600.py
rivalcfg/devices/rival650.py
rivalcfg/devices/rival700.py
rivalcfg/devices/rival95.py
rivalcfg/devices/sensei310.py
rivalcfg/devices/sensei_raw.py
rivalcfg/devices/sensei_ten.py
rivalcfg/handlers/__init__.py
rivalcfg/handlers/choice.py
rivalcfg/handlers/multidpi_range.py
rivalcfg/handlers/none.py
rivalcfg/handlers/range.py
rivalcfg/handlers/reactive_rgbcolor.py
rivalcfg/handlers/rgbcolor.py
rivalcfg/handlers/rgbgradient.py
rivalcfg/handlers/rgbgradientv2.py
rivalcfg/handlers/buttons/__init__.py
rivalcfg/handlers/buttons/buttons.py
rivalcfg/handlers/buttons/layout_multimedia.py
rivalcfg/handlers/buttons/layout_qwerty.py
rivalcfg-4.15.0.dist-info/licenses/LICENSE
rivalcfg-4.15.0.dist-info/METADATA
rivalcfg-4.15.0.dist-info/WHEEL
rivalcfg-4.15.0.dist-info/entry_points.txt
rivalcfg-4.15.0.dist-info/top_level.txt
rivalcfg-4.15.0.dist-info/RECORD
