Metadata-Version: 2.4
Name: rivalcfg
Version: 4.15.0
Summary: Configure SteelSeries gaming mice
Home-page: https://github.com/flozz/rivalcfg
Author: Fabien LOISON
License: WTFPL
Project-URL: Source Code, https://github.com/flozz/rivalcfg
Project-URL: Documentation, https://flozz.github.io/rivalcfg/
Project-URL: Changelog, https://github.com/flozz/rivalcfg#changelog
Project-URL: Issues, https://github.com/flozz/rivalcfg/issues
Project-URL: Chat, https://discord.gg/P77sWhuSs4
Project-URL: Donate, https://github.com/flozz/rivalcfg#supporting-this-project
Keywords: steelseries rival sensei mouse
Platform: Linux
Platform: Windows
License-File: LICENSE
Requires-Dist: hidapi>=0.14.0
Requires-Dist: setuptools
Provides-Extra: dev
Requires-Dist: flake8; extra == "dev"
Requires-Dist: pytest; extra == "dev"
Requires-Dist: Sphinx; extra == "dev"
Requires-Dist: sphinx-rtd-theme; extra == "dev"
Requires-Dist: nox; extra == "dev"
Requires-Dist: black; extra == "dev"
Dynamic: author
Dynamic: description
Dynamic: home-page
Dynamic: keywords
Dynamic: license
Dynamic: license-file
Dynamic: platform
Dynamic: project-url
Dynamic: provides-extra
Dynamic: requires-dist
Dynamic: summary
